eve_auth/__init__.py
eve_auth/admin.py
eve_auth/app_settings.py
eve_auth/apps.py
eve_auth/backends.py
eve_auth/models.py
eve_auth/urls.py
eve_auth/views.py
eve_auth/migrations/0001_initial.py
eve_auth/migrations/__init__.py
eve_auth/templates/eve_auth/user_icon.html
eve_auth/templatetags/__init__.py
eve_auth/templatetags/eve_auth.py
eve_auth/tests/__init__.py
eve_auth/tests/test_admin.py
eve_auth/tests/test_app_settings.py
eve_auth/tests/test_backends.py
eve_auth/tests/test_models.py
eve_auth/tests/test_templatetags.py
eve_auth/tests/test_tools.py
eve_auth/tests/test_views.py
eve_auth/tools/__init__.py
eve_auth/tools/test_tools.py
django_eve_auth-1.3.1.dist-info/LICENSE
django_eve_auth-1.3.1.dist-info/WHEEL
django_eve_auth-1.3.1.dist-info/METADATA
django_eve_auth-1.3.1.dist-info/RECORD
