Metadata-Version: 2.1
Name: django-eve-auth
Version: 1.3.1
Summary: Django user authentication via EVE SSO.
Author-email: Erik Kalkoken <kalkoken87@gmail.com>
Requires-Python: >=3.8
Classifier: Environment :: Web Environment
Classifier: Framework :: Django
Classifier: Framework :: Django :: 3.2
Classifier: Framework :: Django :: 4.2
Classifier: Intended Audience :: Developers
Classifier: License :: OSI Approved :: MIT License
Classifier: Operating System :: OS Independent
Classifier: Programming Language :: Python
Classifier: Programming Language :: Python :: 3.8
Classifier: Programming Language :: Python :: 3.9
Classifier: Programming Language :: Python :: 3.10
Classifier: Programming Language :: Python :: 3.11
Classifier: Topic :: Internet :: WWW/HTTP
Classifier: Topic :: Internet :: WWW/HTTP :: Dynamic Content
Requires-Dist: django-esi>=5
Requires-Dist: Django>=3.2
Project-URL: Changelog, https://gitlab.com/ErikKalkoken/django-eve-auth/-/blob/master/CHANGELOG.md
Project-URL: Documentation, https://django-eve-auth.readthedocs.io/en/latest/
Project-URL: Source, https://gitlab.com/ErikKalkoken/django-eve-auth
Project-URL: Tracker, https://gitlab.com/ErikKalkoken/django-eve-auth/-/issues
